{"v":5,"entries":{"configure-your-project--docs":{"id":"configure-your-project--docs","title":"Configure your project","name":"Docs","importPath":"./src/stories/Configure.mdx","storiesImports":[],"type":"docs","tags":["dev","test","autodocs","unattached-mdx"]},"ui-button--docs":{"id":"ui-button--docs","title":"UI/Button","name":"Docs","importPath":"./src/Button/Button.stories.tsx","type":"docs","tags":["dev","test","autodocs"],"storiesImports":[]},"ui-button--primary":{"type":"story","id":"ui-button--primary","name":"Primary","title":"UI/Button","importPath":"./src/Button/Button.stories.tsx","componentPath":"./src/Button/Button.tsx","tags":["dev","test","autodocs"]},"ui-button--secondary":{"type":"story","id":"ui-button--secondary","name":"Secondary","title":"UI/Button","importPath":"./src/Button/Button.stories.tsx","componentPath":"./src/Button/Button.tsx","tags":["dev","test","autodocs"]},"ui-button--auth":{"type":"story","id":"ui-button--auth","name":"Auth","title":"UI/Button","importPath":"./src/Button/Button.stories.tsx","componentPath":"./src/Button/Button.tsx","tags":["dev","test","autodocs"]},"ui-button--with-icons":{"type":"story","id":"ui-button--with-icons","name":"With Icons","title":"UI/Button","importPath":"./src/Button/Button.stories.tsx","componentPath":"./src/Button/Button.tsx","tags":["dev","test","autodocs"]},"ui-button--all-variants":{"type":"story","id":"ui-button--all-variants","name":"All Variants","title":"UI/Button","importPath":"./src/Button/Button.stories.tsx","componentPath":"./src/Button/Button.tsx","tags":["dev","test","autodocs"]},"ui-postcard--docs":{"id":"ui-postcard--docs","title":"UI/PostCard","name":"Docs","importPath":"./src/Card/Card.stories.tsx","type":"docs","tags":["dev","test","autodocs"],"storiesImports":[]},"ui-postcard--default":{"type":"story","id":"ui-postcard--default","name":"Default","title":"UI/PostCard","importPath":"./src/Card/Card.stories.tsx","componentPath":"./src/Card/Card.tsx","tags":["dev","test","autodocs"]},"ui-postcard--with-long-title":{"type":"story","id":"ui-postcard--with-long-title","name":"With Long Title","title":"UI/PostCard","importPath":"./src/Card/Card.stories.tsx","componentPath":"./src/Card/Card.tsx","tags":["dev","test","autodocs"]},"ui-postcard--multiple-cards":{"type":"story","id":"ui-postcard--multiple-cards","name":"Multiple Cards","title":"UI/PostCard","importPath":"./src/Card/Card.stories.tsx","componentPath":"./src/Card/Card.tsx","tags":["dev","test","autodocs"]},"ui-commentbutton--docs":{"id":"ui-commentbutton--docs","title":"UI/CommentButton","name":"Docs","importPath":"./src/CommentButton/CommentButton.stories.tsx","type":"docs","tags":["dev","test","autodocs"],"storiesImports":[]},"ui-commentbutton--primary":{"type":"story","id":"ui-commentbutton--primary","name":"Primary","title":"UI/CommentButton","importPath":"./src/CommentButton/CommentButton.stories.tsx","componentPath":"./src/CommentButton/CommentButton.tsx","tags":["dev","test","autodocs"]},"ui-commentbutton--small-primary":{"type":"story","id":"ui-commentbutton--small-primary","name":"Small Primary","title":"UI/CommentButton","importPath":"./src/CommentButton/CommentButton.stories.tsx","componentPath":"./src/CommentButton/CommentButton.tsx","tags":["dev","test","autodocs"]},"ui-commentbutton--secondary":{"type":"story","id":"ui-commentbutton--secondary","name":"Secondary","title":"UI/CommentButton","importPath":"./src/CommentButton/CommentButton.stories.tsx","componentPath":"./src/CommentButton/CommentButton.tsx","tags":["dev","test","autodocs"]},"ui-commentbutton--cancel":{"type":"story","id":"ui-commentbutton--cancel","name":"Cancel","title":"UI/CommentButton","importPath":"./src/CommentButton/CommentButton.stories.tsx","componentPath":"./src/CommentButton/CommentButton.tsx","tags":["dev","test","autodocs"]},"ui-commentbutton--all-variants":{"type":"story","id":"ui-commentbutton--all-variants","name":"All Variants","title":"UI/CommentButton","importPath":"./src/CommentButton/CommentButton.stories.tsx","componentPath":"./src/CommentButton/CommentButton.tsx","tags":["dev","test","autodocs"]},"ui-input--docs":{"id":"ui-input--docs","title":"UI/Input","name":"Docs","importPath":"./src/Input/Input.stories.tsx","type":"docs","tags":["dev","test","autodocs"],"storiesImports":[]},"ui-input--default":{"type":"story","id":"ui-input--default","name":"Default","title":"UI/Input","importPath":"./src/Input/Input.stories.tsx","componentPath":"./src/Input/Input.tsx","tags":["dev","test","autodocs"]},"ui-input--email":{"type":"story","id":"ui-input--email","name":"Email","title":"UI/Input","importPath":"./src/Input/Input.stories.tsx","componentPath":"./src/Input/Input.tsx","tags":["dev","test","autodocs"]},"ui-input--password":{"type":"story","id":"ui-input--password","name":"Password","title":"UI/Input","importPath":"./src/Input/Input.stories.tsx","componentPath":"./src/Input/Input.tsx","tags":["dev","test","autodocs"]},"ui-input--all-types":{"type":"story","id":"ui-input--all-types","name":"All Types","title":"UI/Input","importPath":"./src/Input/Input.stories.tsx","componentPath":"./src/Input/Input.tsx","tags":["dev","test","autodocs"]},"components-searchlist--docs":{"id":"components-searchlist--docs","title":"Components/SearchList","name":"Docs","importPath":"./src/SearchList/SearchList.stories.tsx","type":"docs","tags":["dev","test","autodocs"],"storiesImports":[]},"components-searchlist--default":{"type":"story","id":"components-searchlist--default","name":"Default","title":"Components/SearchList","importPath":"./src/SearchList/SearchList.stories.tsx","componentPath":"./src/SearchList/SearchList.tsx","tags":["dev","test","autodocs"]},"components-searchlist--loading":{"type":"story","id":"components-searchlist--loading","name":"Loading","title":"Components/SearchList","importPath":"./src/SearchList/SearchList.stories.tsx","componentPath":"./src/SearchList/SearchList.tsx","tags":["dev","test","autodocs"]},"components-searchlist--error":{"type":"story","id":"components-searchlist--error","name":"Error","title":"Components/SearchList","importPath":"./src/SearchList/SearchList.stories.tsx","componentPath":"./src/SearchList/SearchList.tsx","tags":["dev","test","autodocs"]},"components-searchlist--no-results":{"type":"story","id":"components-searchlist--no-results","name":"No Results","title":"Components/SearchList","importPath":"./src/SearchList/SearchList.stories.tsx","componentPath":"./src/SearchList/SearchList.tsx","tags":["dev","test","autodocs"]},"components-searchlist--no-query":{"type":"story","id":"components-searchlist--no-query","name":"No Query","title":"Components/SearchList","importPath":"./src/SearchList/SearchList.stories.tsx","componentPath":"./src/SearchList/SearchList.tsx","tags":["dev","test","autodocs"]},"components-searchlist--multiple-pages":{"type":"story","id":"components-searchlist--multiple-pages","name":"Multiple Pages","title":"Components/SearchList","importPath":"./src/SearchList/SearchList.stories.tsx","componentPath":"./src/SearchList/SearchList.tsx","tags":["dev","test","autodocs"]},"components-searchlist--all-states":{"type":"story","id":"components-searchlist--all-states","name":"All States","title":"Components/SearchList","importPath":"./src/SearchList/SearchList.stories.tsx","componentPath":"./src/SearchList/SearchList.tsx","tags":["dev","test","autodocs"]},"components-toast--docs":{"id":"components-toast--docs","title":"Components/Toast","name":"Docs","importPath":"./src/Toast/Toast.stories.tsx","type":"docs","tags":["dev","test","autodocs"],"storiesImports":[]},"components-toast--default":{"type":"story","id":"components-toast--default","name":"Default","title":"Components/Toast","importPath":"./src/Toast/Toast.stories.tsx","componentPath":"./src/Toast/Toast.tsx","tags":["dev","test","autodocs"]},"components-toast--success":{"type":"story","id":"components-toast--success","name":"Success","title":"Components/Toast","importPath":"./src/Toast/Toast.stories.tsx","componentPath":"./src/Toast/Toast.tsx","tags":["dev","test","autodocs"]},"components-toast--error":{"type":"story","id":"components-toast--error","name":"Error","title":"Components/Toast","importPath":"./src/Toast/Toast.stories.tsx","componentPath":"./src/Toast/Toast.tsx","tags":["dev","test","autodocs"]},"components-toast--warning":{"type":"story","id":"components-toast--warning","name":"Warning","title":"Components/Toast","importPath":"./src/Toast/Toast.stories.tsx","componentPath":"./src/Toast/Toast.tsx","tags":["dev","test","autodocs"]},"components-toast--long-message":{"type":"story","id":"components-toast--long-message","name":"Long Message","title":"Components/Toast","importPath":"./src/Toast/Toast.stories.tsx","componentPath":"./src/Toast/Toast.tsx","tags":["dev","test","autodocs"]},"components-toast--custom-duration":{"type":"story","id":"components-toast--custom-duration","name":"Custom Duration","title":"Components/Toast","importPath":"./src/Toast/Toast.stories.tsx","componentPath":"./src/Toast/Toast.tsx","tags":["dev","test","autodocs"]},"components-toast--interactive-demo":{"type":"story","id":"components-toast--interactive-demo","name":"Interactive Demo","title":"Components/Toast","importPath":"./src/Toast/Toast.stories.tsx","componentPath":"./src/Toast/Toast.tsx","tags":["dev","test","autodocs"]},"components-toast--all-types":{"type":"story","id":"components-toast--all-types","name":"All Types","title":"Components/Toast","importPath":"./src/Toast/Toast.stories.tsx","componentPath":"./src/Toast/Toast.tsx","tags":["dev","test","autodocs"]},"example-button--docs":{"id":"example-button--docs","title":"Example/Button","name":"Docs","importPath":"./src/stories/Button.stories.ts","type":"docs","tags":["dev","test","autodocs"],"storiesImports":[]},"example-button--primary":{"type":"story","id":"example-button--primary","name":"Primary","title":"Example/Button","importPath":"./src/stories/Button.stories.ts","componentPath":"./src/stories/Button.tsx","tags":["dev","test","autodocs"]},"example-button--secondary":{"type":"story","id":"example-button--secondary","name":"Secondary","title":"Example/Button","importPath":"./src/stories/Button.stories.ts","componentPath":"./src/stories/Button.tsx","tags":["dev","test","autodocs"]},"example-button--large":{"type":"story","id":"example-button--large","name":"Large","title":"Example/Button","importPath":"./src/stories/Button.stories.ts","componentPath":"./src/stories/Button.tsx","tags":["dev","test","autodocs"]},"example-button--small":{"type":"story","id":"example-button--small","name":"Small","title":"Example/Button","importPath":"./src/stories/Button.stories.ts","componentPath":"./src/stories/Button.tsx","tags":["dev","test","autodocs"]},"example-header--docs":{"id":"example-header--docs","title":"Example/Header","name":"Docs","importPath":"./src/stories/Header.stories.ts","type":"docs","tags":["dev","test","autodocs"],"storiesImports":[]},"example-header--logged-in":{"type":"story","id":"example-header--logged-in","name":"Logged In","title":"Example/Header","importPath":"./src/stories/Header.stories.ts","componentPath":"./src/stories/Header.tsx","tags":["dev","test","autodocs"]},"example-header--logged-out":{"type":"story","id":"example-header--logged-out","name":"Logged Out","title":"Example/Header","importPath":"./src/stories/Header.stories.ts","componentPath":"./src/stories/Header.tsx","tags":["dev","test","autodocs"]},"example-page--docs":{"id":"example-page--docs","title":"Example/Page","name":"Docs","importPath":"./src/stories/Page.stories.ts","type":"docs","tags":["dev","test","autodocs"],"storiesImports":[]},"example-page--logged-out":{"type":"story","id":"example-page--logged-out","name":"Logged Out","title":"Example/Page","importPath":"./src/stories/Page.stories.ts","componentPath":"./src/stories/Page.tsx","tags":["dev","test","autodocs"]},"example-page--logged-in":{"type":"story","id":"example-page--logged-in","name":"Logged In","title":"Example/Page","importPath":"./src/stories/Page.stories.ts","componentPath":"./src/stories/Page.tsx","tags":["dev","test","autodocs","play-fn"]}}}